flake8_module_docstring_import.py
flake8_module_docstring_import-0.0.1.dist-info/LICENCE
flake8_module_docstring_import-0.0.1.dist-info/METADATA
flake8_module_docstring_import-0.0.1.dist-info/WHEEL
flake8_module_docstring_import-0.0.1.dist-info/entry_points.txt
flake8_module_docstring_import-0.0.1.dist-info/top_level.txt
flake8_module_docstring_import-0.0.1.dist-info/RECORD
