Metadata-Version: 2.1
Name: flake8-module-docstring-import
Version: 0.0.1
Summary: Very simple flake8 plugin checking if there is exactly one new line between module docstring and imports
Author: djvdq
Maintainer: djvdq
Project-URL: repository, https://codeberg.org/djvdq/flake8_module_docstring_import
License-File: LICENCE
Requires-Dist: flake8
